{
  "transcript": "I think we should just get on with music day and forget about it.",
  "words": [
    {
      "alignedWord": "i",
      "case": "success",
      "end": 0.25,
      "endOffset": 1,
      "phones": [
        {
          "duration": 0.11,
          "phone": "ay_S"
        }
      ],
      "start": 0.14,
      "startOffset": 0,
      "word": "I"
    },
    {
      "alignedWord": "think",
      "case": "success",
      "end": 0.48,
      "endOffset": 7,
      "phones": [
        {
          "duration": 0.07,
          "phone": "th_B"
        },
        {
          "duration": 0.04,
          "phone": "ih_I"
        },
        {
          "duration": 0.06,
          "phone": "ng_I"
        },
        {
          "duration": 0.06,
          "phone": "k_E"
        }
      ],
      "start": 0.25,
      "startOffset": 2,
      "word": "think"
    },
    {
      "alignedWord": "we",
      "case": "success",
      "end": 0.58,
      "endOffset": 10,
      "phones": [
        {
          "duration": 0.03,
          "phone": "w_B"
        },
        {
          "duration": 0.07,
          "phone": "iy_E"
        }
      ],
      "start": 0.48,
      "startOffset": 8,
      "word": "we"
    },
    {
      "alignedWord": "should",
      "case": "success",
      "end": 0.78,
      "endOffset": 17,
      "phones": [
        {
          "duration": 0.06,
          "phone": "sh_B"
        },
        {
          "duration": 0.06,
          "phone": "uh_I"
        },
        {
          "duration": 0.08,
          "phone": "d_E"
        }
      ],
      "start": 0.58,
      "startOffset": 11,
      "word": "should"
    },
    {
      "alignedWord": "just",
      "case": "success",
      "end": 1.24,
      "endOffset": 22,
      "phones": [
        {
          "duration": 0.07,
          "phone": "jh_B"
        },
        {
          "duration": 0.11,
          "phone": "ah_I"
        },
        {
          "duration": 0.13,
          "phone": "s_I"
        },
        {
          "duration": 0.15,
          "phone": "t_E"
        }
      ],
      "start": 0.78,
      "startOffset": 18,
      "word": "just"
    },
    {
      "alignedWord": "get",
      "case": "success",
      "end": 1.57,
      "endOffset": 26,
      "phones": [
        {
          "duration": 0.09,
          "phone": "g_B"
        },
        {
          "duration": 0.08,
          "phone": "eh_I"
        },
        {
          "duration": 0.04,
          "phone": "t_E"
        }
      ],
      "start": 1.36,
      "startOffset": 23,
      "word": "get"
    },
    {
      "alignedWord": "on",
      "case": "success",
      "end": 1.79,
      "endOffset": 29,
      "phones": [
        {
          "duration": 0.13,
          "phone": "aa_B"
        },
        {
          "duration": 0.09,
          "phone": "n_E"
        }
      ],
      "start": 1.57,
      "startOffset": 27,
      "word": "on"
    },
    {
      "alignedWord": "with",
      "case": "success",
      "end": 1.8800000000000001,
      "endOffset": 34,
      "phones": [
        {
          "duration": 0.01,
          "phone": "w_B"
        },
        {
          "duration": 0.01,
          "phone": "ih_I"
        },
        {
          "duration": 0.06,
          "phone": "th_E"
        }
      ],
      "start": 1.8,
      "startOffset": 30,
      "word": "with"
    },
    {
      "alignedWord": "music",
      "case": "success",
      "end": 2.2199999999999998,
      "endOffset": 40,
      "phones": [
        {
          "duration": 0.03,
          "phone": "m_B"
        },
        {
          "duration": 0.07,
          "phone": "y_I"
        },
        {
          "duration": 0.04,
          "phone": "uw_I"
        },
        {
          "duration": 0.07,
          "phone": "z_I"
        },
        {
          "duration": 0.06,
          "phone": "ih_I"
        },
        {
          "duration": 0.07,
          "phone": "k_E"
        }
      ],
      "start": 1.88,
      "startOffset": 35,
      "word": "music"
    },
    {
      "alignedWord": "day",
      "case": "success",
      "end": 2.6500000000000004,
      "endOffset": 44,
      "phones": [
        {
          "duration": 0.09,
          "phone": "d_B"
        },
        {
          "duration": 0.34,
          "phone": "ey_E"
        }
      ],
      "start": 2.22,
      "startOffset": 41,
      "word": "day"
    },
    {
      "alignedWord": "and",
      "case": "success",
      "end": 2.91,
      "endOffset": 48,
      "phones": [
        {
          "duration": 0.1,
          "phone": "ae_B"
        },
        {
          "duration": 0.04,
          "phone": "n_I"
        },
        {
          "duration": 0.07,
          "phone": "d_E"
        }
      ],
      "start": 2.7,
      "startOffset": 45,
      "word": "and"
    },
    {
      "alignedWord": "forget",
      "case": "success",
      "end": 3.18,
      "endOffset": 55,
      "phones": [
        {
          "duration": 0.03,
          "phone": "f_B"
        },
        {
          "duration": 0.08,
          "phone": "er_I"
        },
        {
          "duration": 0.06,
          "phone": "g_I"
        },
        {
          "duration": 0.06,
          "phone": "eh_I"
        },
        {
          "duration": 0.04,
          "phone": "t_E"
        }
      ],
      "start": 2.91,
      "startOffset": 49,
      "word": "forget"
    },
    {
      "alignedWord": "about",
      "case": "success",
      "end": 3.4400000000000004,
      "endOffset": 61,
      "phones": [
        {
          "duration": 0.04,
          "phone": "ah_B"
        },
        {
          "duration": 0.07,
          "phone": "b_I"
        },
        {
          "duration": 0.09,
          "phone": "aw_I"
        },
        {
          "duration": 0.06,
          "phone": "t_E"
        }
      ],
      "start": 3.18,
      "startOffset": 56,
      "word": "about"
    },
    {
      "alignedWord": "it",
      "case": "success",
      "end": 3.58,
      "endOffset": 64,
      "phones": [
        {
          "duration": 0.05,
          "phone": "ih_B"
        },
        {
          "duration": 0.09,
          "phone": "t_E"
        }
      ],
      "start": 3.44,
      "startOffset": 62,
      "word": "it"
    }
  ]
}